{"jufe-202":{"title":"JUFE-202 Revival, Natural I Cup, Legendary Colossal Tit","image":"https://fourhoi.com/jufe-202/cover-n.jpg","path":"en/ju/fe/-2/en-jufe-202.html"},"jufe-205":{"title":"JUFE-205 A Beautiful Slut Tied Up And Fucked By A Man I","image":"https://fourhoi.com/jufe-205/cover-n.jpg","path":"en/ju/fe/-2/en-jufe-205.html"},"jufe-203":{"title":"JUFE-203 Miraculous Curves: Tall Girl With Beautiful Le","image":"https://fourhoi.com/jufe-203/cover-n.jpg","path":"en/ju/fe/-2/en-jufe-203.html"},"jufe-204":{"title":"JUFE-204 A Once-A-Day Limited Edition Secret Inn! The Y","image":"https://fourhoi.com/jufe-204/cover-n.jpg","path":"en/ju/fe/-2/en-jufe-204.html"},"jufe-206":{"title":"JUFE-206 This Secretly Big Tits Plain Jane Girl Who Wor","image":"https://fourhoi.com/jufe-206/cover-n.jpg","path":"en/ju/fe/-2/en-jufe-206.html"},"jotk-087":{"title":"JOTK-087 Haruka - MissAV | Watch HD JAV Online | Free &amp;","image":"https://fourhoi.com/jotk-087/cover-n.jpg","path":"en/jo/tk/-0/en-jotk-087.html"},"jrzd-989":{"title":"JRZD-989 First Shooting Married Woman Document Sakiko N","image":"https://fourhoi.com/jrzd-989/cover-n.jpg","path":"en/jr/zd/-9/en-jrzd-989.html"},"jrzd-990":{"title":"JRZD-990 First Shooting Married Woman Document Tomomi H","image":"https://fourhoi.com/jrzd-990/cover-n.jpg","path":"en/jr/zd/-9/en-jrzd-990.html"},"jrw-021":{"title":"JRW-021 Really Naked Ryokan 16 A hot spring inn that is","image":"https://fourhoi.com/jrw-021/cover-n.jpg","path":"en/jr/w-/02/en-jrw-021.html"},"jul-301":{"title":"JUL-301 The Year, 2020, Summer, Shocking. This Married ","image":"https://fourhoi.com/jul-301/cover-n.jpg","path":"en/ju/l-/30/en-jul-301.html"},"jul-302":{"title":"JUL-302 A Husband And Wife Swapping NTR Shocking Videos","image":"https://fourhoi.com/jul-302/cover-n.jpg","path":"en/ju/l-/30/en-jul-302.html"},"jul-306":{"title":"JUL-306 After Your Graduation... Now That You&#039;re An Adu","image":"https://fourhoi.com/jul-306/cover-n.jpg","path":"en/ju/l-/30/en-jul-306.html"},"jul-307":{"title":"JUL-307 You&#039;ll Want To Grab Hold Of Those G-Cup Titties","image":"https://fourhoi.com/jul-307/cover-n.jpg","path":"en/ju/l-/30/en-jul-307.html"},"jbd-258":{"title":"JBD-258 A Sacrifice To The Freaks Miyu Kanade - MissAV ","image":"https://fourhoi.com/jbd-258/cover-n.jpg","path":"en/jb/d-/25/en-jbd-258.html"},"jul-310":{"title":"JUL-310 My New Stepmom - My Favorite Woman Is Now My St","image":"https://fourhoi.com/jul-310/cover-n.jpg","path":"en/ju/l-/31/en-jul-310.html"},"jul-305":{"title":"JUL-305 I Secretly Want You To Fuck My Wife... - Her Hu","image":"https://fourhoi.com/jul-305/cover-n.jpg","path":"en/ju/l-/30/en-jul-305.html"},"jul-303":{"title":"JUL-303 This Late-Blooming Married Woman Is Blossoming ","image":"https://fourhoi.com/jul-303/cover-n.jpg","path":"en/ju/l-/30/en-jul-303.html"},"jul-304":{"title":"JUL-304 My Mom&#039;s Friends Tsubaki Kato - Tsubaki Kato (K","image":"https://fourhoi.com/jul-304/cover-n.jpg","path":"en/ju/l-/30/en-jul-304.html"},"jul-311":{"title":"JUL-311 This Slug Stepdaddy Will Relentlessly Lick Your","image":"https://fourhoi.com/jul-311/cover-n.jpg","path":"en/ju/l-/31/en-jul-311.html"},"jul-313":{"title":"JUL-313 This Husband And Wife Went On A Training Trip A","image":"https://fourhoi.com/jul-313/cover-n.jpg","path":"en/ju/l-/31/en-jul-313.html"},"jul-314":{"title":"JUL-314 I Left My Lady-Loving Dad With My Pushover Wife","image":"https://fourhoi.com/jul-314/cover-n.jpg","path":"en/ju/l-/31/en-jul-314.html"},"jul-312":{"title":"JUL-312 The Insensitive Married Woman Slut From Next Do","image":"https://fourhoi.com/jul-312/cover-n.jpg","path":"en/ju/l-/31/en-jul-312.html"},"jul-308":{"title":"JUL-308 A Married Woman Who Broke The Rules Of Cuckold ","image":"https://fourhoi.com/jul-308/cover-n.jpg","path":"en/ju/l-/30/en-jul-308.html"},"jul-309":{"title":"JUL-309 With Only 1 Month To Go Until The End Of The Wo","image":"https://fourhoi.com/jul-309/cover-n.jpg","path":"en/ju/l-/30/en-jul-309.html"},"jotk-085":{"title":"JOTK-085 Furthermore - MissAV | Watch HD JAV Online | F","image":"https://fourhoi.com/jotk-085/cover-n.jpg","path":"en/jo/tk/-0/en-jotk-085.html"},"jrzd-988":{"title":"JRZD-988 First Shooting Married Woman Document Ritsuko ","image":"https://fourhoi.com/jrzd-988/cover-n.jpg","path":"en/jr/zd/-9/en-jrzd-988.html"},"jjpp-170":{"title":"JJPP-170 A video of a handsome guy taking a mature woma","image":"https://fourhoi.com/jjpp-170/cover-n.jpg","path":"en/jj/pp/-1/en-jjpp-170.html"},"jjpp-171":{"title":"JJPP-171 A video of a handsome guy taking a mature woma","image":"https://fourhoi.com/jjpp-171/cover-n.jpg","path":"en/jj/pp/-1/en-jjpp-171.html"}}