{"hmdn-294":"en/hm/dn/-2/en-hmdn-294.html","hery-105":"en/he/ry/-1/en-hery-105.html","hint-414":"en/hi/nt/-4/en-hint-414.html","hint-413":"en/hi/nt/-4/en-hint-413.html","hjmo-440":"en/hj/mo/-4/en-hjmo-440.html","hhkl-063":"en/hh/kl/-0/en-hhkl-063.html","hjmo-439":"en/hj/mo/-4/en-hjmo-439.html","hjmo-438":"en/hj/mo/-4/en-hjmo-438.html","honb-189":"en/ho/nb/-1/en-honb-189.html","hypn-026":"en/hy/pn/-0/en-hypn-026.html","hoi-127":"en/ho/i-/12/en-hoi-127.html","hmdn-293":"en/hm/dn/-2/en-hmdn-293.html","htut-432":"en/ht/ut/-4/en-htut-432.html","hlan-008":"en/hl/an/-0/en-hlan-008.html","htut-435":"en/ht/ut/-4/en-htut-435.html","hgot-053":"en/hg/ot/-0/en-hgot-053.html","hgot-052":"en/hg/ot/-0/en-hgot-052.html","hgot-054":"en/hg/ot/-0/en-hgot-054.html","htut-436":"en/ht/ut/-4/en-htut-436.html","htut-438":"en/ht/ut/-4/en-htut-438.html","hgot-055":"en/hg/ot/-0/en-hgot-055.html","hrv-042":"en/hr/v-/04/en-hrv-042.html","hsm-020":"en/hs/m-/02/en-hsm-020.html","hoi-126":"en/ho/i-/12/en-hoi-126.html","hbad-554":"en/hb/ad/-5/en-hbad-554.html","hawa-222":"en/ha/wa/-2/en-hawa-222.html","hawa-223":"en/ha/wa/-2/en-hawa-223.html","hbad-553":"en/hb/ad/-5/en-hbad-553.html","hbad-555":"en/hb/ad/-5/en-hbad-555.html","hisn-008":"en/hi/sn/-0/en-hisn-008.html","hmdn-292":"en/hm/dn/-2/en-hmdn-292.html","hunta-839":"en/hu/nt/a-/en-hunta-839.html","hunta-847":"en/hu/nt/a-/en-hunta-847.html","hunta-844":"en/hu/nt/a-/en-hunta-844.html","hint-412":"en/hi/nt/-4/en-hint-412.html","hunbl-012":"en/hu/nb/l-/en-hunbl-012.html","hunta-846":"en/hu/nt/a-/en-hunta-846.html","hunta-843":"en/hu/nt/a-/en-hunta-843.html","hunta-845":"en/hu/nt/a-/en-hunta-845.html","hunta-842":"en/hu/nt/a-/en-hunta-842.html","hunta-840":"en/hu/nt/a-/en-hunta-840.html","hunta-838":"en/hu/nt/a-/en-hunta-838.html","hunta-841":"en/hu/nt/a-/en-hunta-841.html","hunbl-011":"en/hu/nb/l-/en-hunbl-011.html","hhkl-062":"en/hh/kl/-0/en-hhkl-062.html","hhgt-003":"en/hh/gt/-0/en-hhgt-003.html","hhap-003":"en/hh/ap/-0/en-hhap-003.html","hypn-025":"en/hy/pn/-0/en-hypn-025.html","hodv-21506":"en/ho/dv/-2/en-hodv-21506.html","hoi-124":"en/ho/i-/12/en-hoi-124.html","hodv-21509":"en/ho/dv/-2/en-hodv-21509.html","hmdn-291":"en/hm/dn/-2/en-hmdn-291.html","hodv-21505":"en/ho/dv/-2/en-hodv-21505.html","hodv-21508":"en/ho/dv/-2/en-hodv-21508.html","hodv-21507":"en/ho/dv/-2/en-hodv-21507.html","hoi-125":"en/ho/i-/12/en-hoi-125.html","hone-252":"en/ho/ne/-2/en-hone-252.html","hthd-179":"en/ht/hd/-1/en-hthd-179.html","hr-002":"en/hr/-0/02/en-hr-002.html","hz-004":"en/hz/-0/04/en-hz-004.html","hdka-216":"en/hd/ka/-2/en-hdka-216.html","hikr-175":"en/hi/kr/-1/en-hikr-175.html","hikr-174":"en/hi/kr/-1/en-hikr-174.html","hmdn-290":"en/hm/dn/-2/en-hmdn-290.html"}